gemini_faf_mcp/__init__.py
gemini_faf_mcp/client.py
gemini_faf_mcp/parser.py
gemini_faf_mcp-1.0.2.dist-info/METADATA
gemini_faf_mcp-1.0.2.dist-info/WHEEL
gemini_faf_mcp-1.0.2.dist-info/top_level.txt
gemini_faf_mcp-1.0.2.dist-info/RECORD
