Metadata-Version: 2.4
Name: gemini-faf-mcp
Version: 1.0.2
Summary: Universal Context Landing Pad for FAF (Foundational AI-context Format)
Author-email: wolfejam <james@wolfejam.dev>
License: MIT
Project-URL: Homepage, https://github.com/Wolfe-Jam/gemini-faf-mcp
Project-URL: Glory Wall, https://faf-landing.vercel.app/glory.html
Project-URL: FAF Specification, https://faf.one
Project-URL: IANA Registration, https://www.iana.org/assignments/media-types/application/vnd.faf+yaml
Project-URL: Bug Tracker, https://github.com/Wolfe-Jam/gemini-faf-mcp/issues
Keywords: faf,mcp,gemini,ai-context,model-context-protocol
Classifier: Programming Language :: Python :: 3
Classifier: Programming Language :: Python :: 3.12
Classifier: License :: OSI Approved :: MIT License
Classifier: Operating System :: OS Independent
Classifier: Development Status :: 5 - Production/Stable
Classifier: Intended Audience :: Developers
Classifier: Topic :: Software Development :: Libraries :: Python Modules
Requires-Python: >=3.12
Requires-Dist: functions-framework>=3.0.0
Requires-Dist: google-cloud-bigquery>=3.0.0
Requires-Dist: google-cloud-secret-manager>=2.0.0
Requires-Dist: pyyaml>=6.0
Requires-Dist: requests>=2.28.0
Provides-Extra: dev
Requires-Dist: pytest>=7.0.0; extra == "dev"
Requires-Dist: pytest-cov>=4.0.0; extra == "dev"
